_syncrng.cpython-312-x86_64-linux-gnu.so
SyncRNG/__init__.py
SyncRNG/__version__.py
syncrng-1.3.4.dist-info/METADATA
syncrng-1.3.4.dist-info/WHEEL
syncrng-1.3.4.dist-info/top_level.txt
syncrng-1.3.4.dist-info/RECORD
syncrng-1.3.4.dist-info/licenses/LICENSE
